{   "metadata": 
[
 {
   "fileId": "18LBSrJFmqUOZYCt2dfCmeq_mty6BvOS6",
   "artist": "尸解",
   "album": "攫 筐",
   "albumArt": "https://raw.githubusercontent.com/yonesaku/googledriveextension/refs/heads/main/Paul%20Kim%20-%20Star%20(3rd%20Mini%20Album)%20Albumcover%20Artwork%20-%20heesoo%20kim.jpg",
   "genre": " 娥 叼葛筐",
   "year": 2024
 },
 {
   "fileId": "1hkly6esGj-BKN7wXBCz_TDBVWUGgn4u5",
   "artist": "尸解",
   "album": "攫 筐",
   "albumArt": "https://raw.githubusercontent.com/yonesaku/googledriveextension/refs/heads/main/Paul%20Kim%20-%20Star%20(3rd%20Mini%20Album)%20Albumcover%20Artwork%20-%20heesoo%20kim.jpg",
   "genre": " 娥 叼葛筐",
   "year": 2024
 },
 {
   "fileId": "1Ylcod9rnQDUDDK9won9Jh1_9YznO8-Vr",
   "artist": "尸解",
   "album": "攫 筐",
   "albumArt": "https://raw.githubusercontent.com/yonesaku/googledriveextension/refs/heads/main/Paul%20Kim%20-%20Star%20(3rd%20Mini%20Album)%20Albumcover%20Artwork%20-%20heesoo%20kim.jpg",
   "genre": " 娥 叼葛筐",
   "year": 2024
 },
 {
   "fileId": "1w1IGT_Co-jN-Ia2TY37-ZH5RHrAHmwnd",
   "artist": "尸解",
   "album": "攫 筐",
   "albumArt": "https://raw.githubusercontent.com/yonesaku/googledriveextension/refs/heads/main/Paul%20Kim%20-%20Star%20(3rd%20Mini%20Album)%20Albumcover%20Artwork%20-%20heesoo%20kim.jpg",
   "genre": " 娥 叼葛筐",
   "year": 2024
 },
 {
   "fileId": "1jeex0OEdv4VIJ8f7x-Xf14PTjCt0_r_y",
   "artist": "尸解",
   "album": "攫 筐",
   "albumArt": "https://raw.githubusercontent.com/yonesaku/googledriveextension/refs/heads/main/Paul%20Kim%20-%20Star%20(3rd%20Mini%20Album)%20Albumcover%20Artwork%20-%20heesoo%20kim.jpg",
   "genre": " 娥 叼葛筐",
   "year": 2024
 },
 {
   "fileId": "1US-EIGa1Zxf_Ch2nbowOMyouhHhPCwBF",
   "artist": "尸解",
   "album": "攫 筐",
   "albumArt": "https://raw.githubusercontent.com/yonesaku/googledriveextension/refs/heads/main/Paul%20Kim%20-%20Star%20(3rd%20Mini%20Album)%20Albumcover%20Artwork%20-%20heesoo%20kim.jpg",
   "genre": " 娥 叼葛筐",
   "year": 2024
 },
 {
   "fileId": "145UNEOlVIduWNBh2FKeYKwDfZtgwtNoK",
   "artist": "尸解",
   "album": "攫 筐",
   "albumArt": "https://raw.githubusercontent.com/yonesaku/googledriveextension/refs/heads/main/Paul%20Kim%20-%20Star%20(3rd%20Mini%20Album)%20Albumcover%20Artwork%20-%20heesoo%20kim.jpg",
   "genre": " 娥 叼葛筐",
   "year": 2024
 },
 {
   "fileId": "1qfbrkn5Shv4ngNK5Mk2VxZhzEnylFdJ0",
   "artist": "尸解",
   "album": "攫 筐",
   "albumArt": "https://raw.githubusercontent.com/yonesaku/googledriveextension/refs/heads/main/Paul%20Kim%20-%20Star%20(3rd%20Mini%20Album)%20Albumcover%20Artwork%20-%20heesoo%20kim.jpg",
   "genre": " 娥 叼葛筐",
   "year": 2024
 },
 {
   "fileId": "1v3BSdGwwu1f3P4eI6mZyD9nQTVpHo7UJ",
   "artist": "尸解",
   "album": "攫 筐",
   "albumArt": "https://raw.githubusercontent.com/yonesaku/googledriveextension/refs/heads/main/Paul%20Kim%20-%20Star%20(3rd%20Mini%20Album)%20Albumcover%20Artwork%20-%20heesoo%20kim.jpg",
   "genre": " 娥 叼葛筐",
   "year": 2024
 },
 {
   "fileId": "1m_1IzRhwozG4PiGhKATS7g_kMk7Dq0UG",
   "artist": "尸解",
   "album": "攫 筐",
   "albumArt": "https://raw.githubusercontent.com/yonesaku/googledriveextension/refs/heads/main/Paul%20Kim%20-%20Star%20(3rd%20Mini%20Album)%20Albumcover%20Artwork%20-%20heesoo%20kim.jpg",
   "genre": " 娥 叼葛筐",
   "year": 2024
 },
 {
   "fileId": "1K7nQGUaqD_GQHiuoKDiVXw--45Jsboaf",
   "artist": "尸解",
   "album": "攫 筐",
   "albumArt": "https://raw.githubusercontent.com/yonesaku/googledriveextension/refs/heads/main/Paul%20Kim%20-%20Star%20(3rd%20Mini%20Album)%20Albumcover%20Artwork%20-%20heesoo%20kim.jpg",
   "genre": " 娥 叼葛筐",
   "year": 2024
 },
 {
   "fileId": "1QNJBvhYMb6_MtGLVDYLbqEp8_N6dpiVM",
   "artist": "尸解",
   "album": "攫 筐",
   "albumArt": "https://raw.githubusercontent.com/yonesaku/googledriveextension/refs/heads/main/Paul%20Kim%20-%20Star%20(3rd%20Mini%20Album)%20Albumcover%20Artwork%20-%20heesoo%20kim.jpg",
   "genre": " 娥 叼葛筐",
   "year": 2024
 },
 {
   "fileId": "1wH3kTlqhRKoS0Pju0qzafbq-LBR0PE40",
   "artist": "尸解",
   "album": "攫 筐",
   "albumArt": "https://raw.githubusercontent.com/yonesaku/googledriveextension/refs/heads/main/Paul%20Kim%20-%20Star%20(3rd%20Mini%20Album)%20Albumcover%20Artwork%20-%20heesoo%20kim.jpg",
   "genre": " 娥 叼葛筐",
   "year": 2024
 },
 {
   "fileId": "1xyIfJGRson9xZPJraSYc_jRGn1_6x0yf",
   "artist": "尸解",
   "album": "攫 筐",
   "albumArt": "https://raw.githubusercontent.com/yonesaku/googledriveextension/refs/heads/main/Paul%20Kim%20-%20Star%20(3rd%20Mini%20Album)%20Albumcover%20Artwork%20-%20heesoo%20kim.jpg",
   "genre": " 娥 叼葛筐",
   "year": 2024
 },
 {
   "fileId": "1tQX_VgLVzShyGKltwis1qYgrzMnpvdPI",
   "artist": "尸解",
   "album": "攫 筐",
   "albumArt": "https://raw.githubusercontent.com/yonesaku/googledriveextension/refs/heads/main/Paul%20Kim%20-%20Star%20(3rd%20Mini%20Album)%20Albumcover%20Artwork%20-%20heesoo%20kim.jpg",
   "genre": " 娥 叼葛筐",
   "year": 2024
 },
 {
   "fileId": "10iNwttdNJj_t7BZqnJ7-DDQSigqfK6Bz",
   "artist": "尸解",
   "album": "攫 筐",
   "albumArt": "https://raw.githubusercontent.com/yonesaku/googledriveextension/refs/heads/main/Paul%20Kim%20-%20Star%20(3rd%20Mini%20Album)%20Albumcover%20Artwork%20-%20heesoo%20kim.jpg",
   "genre": " 娥 叼葛筐",
   "year": 2024
 },
 {
   "fileId": "1gLM1-XIHldygsyLLl9GgNNMSCU1m3WIv",
   "artist": "尸解",
   "album": "攫 筐",
   "albumArt": "https://raw.githubusercontent.com/yonesaku/googledriveextension/refs/heads/main/Paul%20Kim%20-%20Star%20(3rd%20Mini%20Album)%20Albumcover%20Artwork%20-%20heesoo%20kim.jpg",
   "genre": " 娥 叼葛筐",
   "year": 2024
 },
 {
   "fileId": "1GWT_0bwMXGDFe8GN_GopDKnaJGq-tQbT",
   "artist": "尸解",
   "album": "攫 筐",
   "albumArt": "https://raw.githubusercontent.com/yonesaku/googledriveextension/refs/heads/main/Paul%20Kim%20-%20Star%20(3rd%20Mini%20Album)%20Albumcover%20Artwork%20-%20heesoo%20kim.jpg",
   "genre": " 娥 叼葛筐",
   "year": 2024
 },
 {
   "fileId": "1Ov1Z9n8DvQbGFpdW3bcJZMXB_FUJM_01",
   "artist": "尸解",
   "album": "攫 筐",
   "albumArt": "https://raw.githubusercontent.com/yonesaku/googledriveextension/refs/heads/main/Paul%20Kim%20-%20Star%20(3rd%20Mini%20Album)%20Albumcover%20Artwork%20-%20heesoo%20kim.jpg",
   "genre": " 娥 叼葛筐",
   "year": 2024
 },
 {
   "fileId": "1wPw2nv6OtsJ6NXK_spMGmB7zqxhT5I-c",
   "artist": "尸解",
   "album": "攫 筐",
   "albumArt": "https://raw.githubusercontent.com/yonesaku/googledriveextension/refs/heads/main/Paul%20Kim%20-%20Star%20(3rd%20Mini%20Album)%20Albumcover%20Artwork%20-%20heesoo%20kim.jpg",
   "genre": " 娥 叼葛筐",
   "year": 2024
 },
 {
   "fileId": "1aZ3JrZR6FJgwrZgEjO8nW4ZB9CszROQW",
   "artist": "尸解",
   "album": "攫 筐",
   "albumArt": "https://raw.githubusercontent.com/yonesaku/googledriveextension/refs/heads/main/Paul%20Kim%20-%20Star%20(3rd%20Mini%20Album)%20Albumcover%20Artwork%20-%20heesoo%20kim.jpg",
   "genre": " 娥 叼葛筐",
   "year": 2024
 },
 {
   "fileId": "1zAatT2vBZRLzGmkGkQIQEi3gaJpy8LiW",
   "artist": "尸解",
   "album": "攫 筐",
   "albumArt": "https://raw.githubusercontent.com/yonesaku/googledriveextension/refs/heads/main/Paul%20Kim%20-%20Star%20(3rd%20Mini%20Album)%20Albumcover%20Artwork%20-%20heesoo%20kim.jpg",
   "genre": " 娥 叼葛筐",
   "year": 2024
 },
 {
   "fileId": "1I4RUUaEX2C9zpjKoex_wZhZ2MaAVLPR2",
   "artist": "尸解",
   "album": "攫 筐",
   "albumArt": "https://raw.githubusercontent.com/yonesaku/googledriveextension/refs/heads/main/Paul%20Kim%20-%20Star%20(3rd%20Mini%20Album)%20Albumcover%20Artwork%20-%20heesoo%20kim.jpg",
   "genre": " 娥 叼葛筐",
   "year": 2024
 },
 {
   "fileId": "1U0d7SR_fvQtpDsCNNhkGF0zvcHHO2lJ1",
   "artist": "尸解",
   "album": "攫 筐",
   "albumArt": "https://raw.githubusercontent.com/yonesaku/googledriveextension/refs/heads/main/Paul%20Kim%20-%20Star%20(3rd%20Mini%20Album)%20Albumcover%20Artwork%20-%20heesoo%20kim.jpg",
   "genre": " 娥 叼葛筐",
   "year": 2024
 },
 {
   "fileId": "1AtgYe2Yy3nd7GV5Ee4Rg8lxG5YMhLejn",
   "artist": "尸解",
   "album": "攫 筐",
   "albumArt": "https://raw.githubusercontent.com/yonesaku/googledriveextension/refs/heads/main/Paul%20Kim%20-%20Star%20(3rd%20Mini%20Album)%20Albumcover%20Artwork%20-%20heesoo%20kim.jpg",
   "genre": " 娥 叼葛筐",
   "year": 2024
 },
 {
   "fileId": "10fFt_f472c1XjeUmWVF5gc26XPzcw8wq",
   "artist": "尸解",
   "album": "攫 筐",
   "albumArt": "https://raw.githubusercontent.com/yonesaku/googledriveextension/refs/heads/main/Paul%20Kim%20-%20Star%20(3rd%20Mini%20Album)%20Albumcover%20Artwork%20-%20heesoo%20kim.jpg",
   "genre": " 娥 叼葛筐",
   "year": 2024
 },
 {
   "fileId": "1Us9uO0B25RubC5XcIHyGu6oKJLr56mj1",
   "artist": "尸解",
   "album": "攫 筐",
   "albumArt": "https://raw.githubusercontent.com/yonesaku/googledriveextension/refs/heads/main/Paul%20Kim%20-%20Star%20(3rd%20Mini%20Album)%20Albumcover%20Artwork%20-%20heesoo%20kim.jpg",
   "genre": " 娥 叼葛筐",
   "year": 2024
 },
 {
   "fileId": "1wGi7hQ4kuhpvnQYDoo9gs0NW5DR-4hX0",
   "artist": "尸解",
   "album": "攫 筐",
   "albumArt": "https://raw.githubusercontent.com/yonesaku/googledriveextension/refs/heads/main/Paul%20Kim%20-%20Star%20(3rd%20Mini%20Album)%20Albumcover%20Artwork%20-%20heesoo%20kim.jpg",
   "genre": " 娥 叼葛筐",
   "year": 2024
 },
 {
   "fileId": "15kB5sNxDHryG9eYe0LMXLnKiQEAMS7gz",
   "artist": "尸解",
   "album": "攫 筐",
   "albumArt": "https://raw.githubusercontent.com/yonesaku/googledriveextension/refs/heads/main/Paul%20Kim%20-%20Star%20(3rd%20Mini%20Album)%20Albumcover%20Artwork%20-%20heesoo%20kim.jpg",
   "genre": " 娥 叼葛筐",
   "year": 2024
 },
 {
   "fileId": "1oAvasLbnDzaJkf2bRTshyRJKxoi45e0x",
   "artist": "尸解",
   "album": "攫 筐",
   "albumArt": "https://raw.githubusercontent.com/yonesaku/googledriveextension/refs/heads/main/Paul%20Kim%20-%20Star%20(3rd%20Mini%20Album)%20Albumcover%20Artwork%20-%20heesoo%20kim.jpg",
   "genre": " 娥 叼葛筐",
   "year": 2024
 },
 {
   "fileId": "1M1-l7QkjPGWHjIGKTaSKjIT6QkXYDXto",
   "artist": "Bad decisions .Poor choices",
   "album": "The FALLING Saga : Act II",
   "albumArt": "https://raw.githubusercontent.com/yonesaku/googledriveextension/refs/heads/main/ACT%202.png",
   "genre": "clinically insane, crazy, mentally instable",
   "year": 2025
 },
 {
   "fileId": "12r-UVPxkyaryO92MWIppGYL5OTklAhHK",
   "artist": "Bad decisions .Poor choices",
   "album": "The FALLING Saga : Act II",
   "albumArt": "https://raw.githubusercontent.com/yonesaku/googledriveextension/refs/heads/main/ACT%202.png",
   "genre": "clinically insane, crazy, mentally instable",
   "year": 2025
 },
 {
   "fileId": "1hKKhgTnpYtvpn_c7ZLduGan2I9RkUgMv",
   "artist": "Bad decisions .Poor choices",
   "album": "The FALLING Saga : Act II",
   "albumArt": "https://raw.githubusercontent.com/yonesaku/googledriveextension/refs/heads/main/ACT%202.png",
   "genre": "clinically insane, crazy, mentally instable",
   "year": 2025
 },
 {
   "fileId": "154RptJ4NqzvxYBKL-Xh_F3EBmlJiINM3",
   "artist": "Bad decisions .Poor choices",
   "album": "The FALLING Saga : Act II",
   "albumArt": "https://raw.githubusercontent.com/yonesaku/googledriveextension/refs/heads/main/ACT%202.png",
   "genre": "clinically insane, crazy, mentally instable",
   "year": 2025
 },
 {
   "fileId": "1kNR-OcgJN7_VLwRUOJ5D2HSFN8aaKehK",
   "artist": "Bad decisions .Poor choices",
   "album": "The FALLING Saga : Act II",
   "albumArt": "https://raw.githubusercontent.com/yonesaku/googledriveextension/refs/heads/main/ACT%202.png",
   "genre": "clinically insane, crazy, mentally instable",
   "year": 2025
 },
 {
   "fileId": "1Nrn49w3QSvOJ688xaBbG7jeuF8IrjAeG",
   "artist": "Bad decisions .Poor choices",
   "album": "The FALLING Saga : Act II",
   "albumArt": "https://raw.githubusercontent.com/yonesaku/googledriveextension/refs/heads/main/ACT%202.png",
   "genre": "clinically insane, crazy, mentally instable",
   "year": 2025
 },
 {
   "fileId": "1NL4P7Ndl8Sanrnqbg4NGjpZYwoRhNLd9",
   "artist": "Bad decisions .Poor choices",
   "album": "The FALLING Saga : Act II",
   "albumArt": "https://raw.githubusercontent.com/yonesaku/googledriveextension/refs/heads/main/ACT%202.png",
   "genre": "clinically insane, crazy, mentally instable",
   "year": 2025
 },
 {
   "fileId": "1U-17PGQHOeyI4zuUE2X3vcASmsu5y_o7",
   "artist": "Bad decisions .Poor choices",
   "album": "The FALLING Saga : Act II",
   "albumArt": "https://raw.githubusercontent.com/yonesaku/googledriveextension/refs/heads/main/ACT%202.png",
   "genre": "clinically insane, crazy, mentally instable",
   "year": 2025
 },
 {
   "fileId": "1cBvn7wRZmG-jcKneZ7jWPL4UYaxsmyll",
   "artist": "Bad decisions .Poor choices",
   "album": "The FALLING Saga : Act II",
   "albumArt": "https://raw.githubusercontent.com/yonesaku/googledriveextension/refs/heads/main/ACT%202.png",
   "genre": "clinically insane, crazy, mentally instable",
   "year": 2025
 },
 {
   "fileId": "1s8FZWWTMpkPjaOHQJ13Oz5iavpVlWBpY",
   "artist": "Bad decisions .Poor choices",
   "album": "The FALLING Saga : Act II",
   "albumArt": "https://raw.githubusercontent.com/yonesaku/googledriveextension/refs/heads/main/ACT%202.png",
   "genre": "clinically insane, crazy, mentally instable",
   "year": 2025
 },
 {
   "fileId": "1XWLMVOMxrFt3_iu8XMmZ-zSE56nD_-ZW",
   "artist": "Bad decisions .Poor choices",
   "album": "The FALLING Saga : Act II",
   "albumArt": "https://raw.githubusercontent.com/yonesaku/googledriveextension/refs/heads/main/ACT%202.png",
   "genre": "clinically insane, crazy, mentally instable",
   "year": 2025
 },
 {
   "fileId": "17G6XcvWrKf5iMRpwRnoGd9x4Ni3HniUZ",
   "artist": "Bad decisions .Poor choices",
   "album": "The FALLING Saga : Act II",
   "albumArt": "https://raw.githubusercontent.com/yonesaku/googledriveextension/refs/heads/main/ACT%202.png",
   "genre": "clinically insane, crazy, mentally instable",
   "year": 2025
 },
 {
   "fileId": "1lOKyfgkmnIqTAvnqxRuOYwg510zie8r0",
   "artist": "Bad decisions .Poor choices",
   "album": "The FALLING Saga : Act II",
   "albumArt": "https://raw.githubusercontent.com/yonesaku/googledriveextension/refs/heads/main/ACT%202.png",
   "genre": "clinically insane, crazy, mentally instable",
   "year": 2025
 },
 {
   "fileId": "1xRWyeGsi3OYwKbenkCXUriRAqDbwykiG",
   "artist": "Bad decisions .Poor choices",
   "album": "The FALLING Saga : Act II",
   "albumArt": "https://raw.githubusercontent.com/yonesaku/googledriveextension/refs/heads/main/ACT%202.png",
   "genre": "clinically insane, crazy, mentally instable",
   "year": 2025
 },
 {
   "fileId": "1vBT-JNWgTuGC-p6YAIOIGS6NHCr_yKMf",
   "artist": "Bad decisions .Poor choices",
   "album": "The FALLING Saga : Act II",
   "albumArt": "https://raw.githubusercontent.com/yonesaku/googledriveextension/refs/heads/main/ACT%202.png",
   "genre": "clinically insane, crazy, mentally instable",
   "year": 2025
 },
 {
   "fileId": "15YPzKQyN7STk5ZJ2IONmTYEaCHs7DLLy",
   "artist": "Bad decisions .Poor choices",
   "album": "The FALLING Saga : Act II",
   "albumArt": "https://raw.githubusercontent.com/yonesaku/googledriveextension/refs/heads/main/ACT%202.png",
   "genre": "clinically insane, crazy, mentally instable",
   "year": 2025
 },
 {
   "fileId": "1WhjkJHimtqgKmYbLPhW2_mVt8p5i2BWw",
   "artist": "Bad decisions .Poor choices",
   "album": "The FALLING Saga : Act II",
   "albumArt": "https://raw.githubusercontent.com/yonesaku/googledriveextension/refs/heads/main/ACT%202.png",
   "genre": "clinically insane, crazy, mentally instable",
   "year": 2025
 },
 {
   "fileId": "106tN3Q5usCaZwEOCWOGfcjT8M3Z3RK8i",
   "artist": "Bad decisions .Poor choices",
   "album": "The FALLING Saga : Act II",
   "albumArt": "https://raw.githubusercontent.com/yonesaku/googledriveextension/refs/heads/main/ACT%202.png",
   "genre": "clinically insane, crazy, mentally instable",
   "year": 2025
 },
 {
   "fileId": "1wSWF2GLw1-zKS9IcfXz1Zh474EQk4kUJ",
   "artist": "Bad decisions .Poor choices",
   "album": "The FALLING Saga : Act II",
   "albumArt": "https://raw.githubusercontent.com/yonesaku/googledriveextension/refs/heads/main/ACT%202.png",
   "genre": "clinically insane, crazy, mentally instable",
   "year": 2025
 },
 {
   "fileId": "1wUvgZlxOywGu4QLRyMQ_ABDRdjEkvC0R",
   "artist": "Bad decisions .Poor choices",
   "album": "The FALLING Saga : Act II",
   "albumArt": "https://raw.githubusercontent.com/yonesaku/googledriveextension/refs/heads/main/ACT%202.png",
   "genre": "clinically insane, crazy, mentally instable",
   "year": 2025
 },
 {
   "fileId": "1eqbDZx7PpvO1ty_a6Hwin8VjNITvhQmT",
   "artist": "Bad decisions .Poor choices",
   "album": "The FALLING Saga : Act II",
   "albumArt": "https://raw.githubusercontent.com/yonesaku/googledriveextension/refs/heads/main/ACT%202.png",
   "genre": "clinically insane, crazy, mentally instable",
   "year": 2025
 },
 {
   "fileId": "18kRSYMVCU9hxlEGU3n3C0f6L-q1oS7US",
   "artist": "Bad decisions .Poor choices",
   "album": "The FALLING Saga : Act II",
   "albumArt": "https://raw.githubusercontent.com/yonesaku/googledriveextension/refs/heads/main/ACT%202.png",
   "genre": "clinically insane, crazy, mentally instable",
   "year": 2025
 },
 {
   "fileId": "1A2srWn3R9xDvFqfd1smH10g2nxJZ1o0X",
   "artist": "Bad decisions .Poor choices",
   "album": "The FALLING Saga : Act II",
   "albumArt": "https://raw.githubusercontent.com/yonesaku/googledriveextension/refs/heads/main/ACT%202.png",
   "genre": "clinically insane, crazy, mentally instable",
   "year": 2025
 },
 {
   "fileId": "1KSRS9Az07yhsSu4tlmkjx5RwyShgyY4R",
   "artist": "Bad decisions .Poor choices",
   "album": "The FALLING Saga : Act II",
   "albumArt": "https://raw.githubusercontent.com/yonesaku/googledriveextension/refs/heads/main/ACT%202.png",
   "genre": "clinically insane, crazy, mentally instable",
   "year": 2025
 },
 {
   "fileId": "1Pt1ccLyqfZDRvSFsUx6hXYNLYuJf6Oxn",
   "artist": "Bad decisions .Poor choices",
   "album": "The FALLING Saga : Act II",
   "albumArt": "https://raw.githubusercontent.com/yonesaku/googledriveextension/refs/heads/main/ACT%202.png",
   "genre": "clinically insane, crazy, mentally instable",
   "year": 2025
 },
 {
   "fileId": "13U4ClLMY961UPZ3SXtxCCqy8HOzNoOX4",
   "artist": "Bad decisions .Poor choices",
   "album": "The FALLING Saga : Act II",
   "albumArt": "https://raw.githubusercontent.com/yonesaku/googledriveextension/refs/heads/main/ACT%202.png",
   "genre": "clinically insane, crazy, mentally instable",
   "year": 2025
 },
 {
   "fileId": "1pvHg3XM6h5E-7y8Wye0vg3SKLviC_Mgw",
   "artist": "Bad decisions .Poor choices",
   "album": "The FALLING Saga : Act II",
   "albumArt": "https://raw.githubusercontent.com/yonesaku/googledriveextension/refs/heads/main/ACT%202.png",
   "genre": "clinically insane, crazy, mentally instable",
   "year": 2025
 },
 {
   "fileId": "1mqkGMMNW3a9ZEMrUkm8LSNCaeb75EVN_",
   "artist": "Bad decisions .Poor choices",
   "album": "The FALLING Saga : Act II",
   "albumArt": "https://raw.githubusercontent.com/yonesaku/googledriveextension/refs/heads/main/ACT%202.png",
   "genre": "clinically insane, crazy, mentally instable",
   "year": 2025
 },
 {
   "fileId": "1nYx0ucnzjgX68OXFcI2Tt7mByAQ1xJa-",
   "artist": "Bad decisions .Poor choices",
   "album": "The FALLING Saga : Act II",
   "albumArt": "https://raw.githubusercontent.com/yonesaku/googledriveextension/refs/heads/main/ACT%202.png",
   "genre": "clinically insane, crazy, mentally instable",
   "year": 2025
 },
 {
   "fileId": "1cEGOuv6OwX3rxXvFVazE28Iy1dAgNBs9",
   "artist": "Bad decisions .Poor choices",
   "album": "The FALLING Saga : Act II",
   "albumArt": "https://raw.githubusercontent.com/yonesaku/googledriveextension/refs/heads/main/ACT%202.png",
   "genre": "clinically insane, crazy, mentally instable",
   "year": 2025
 },
 {
   "fileId": "1sQX7EZo5Ca7QR2LV3tvU8gmHY272uDe7",
   "artist": "Bad decisions .Poor choices",
   "album": "The FALLING Saga : Act II",
   "albumArt": "https://raw.githubusercontent.com/yonesaku/googledriveextension/refs/heads/main/ACT%202.png",
   "genre": "clinically insane, crazy, mentally instable",
   "year": 2025
 },
 {
   "fileId": "1BMd-pXyjSEP-GFxP8ZZmIE5hJYzIusMw",
   "artist": "Bad decisions .Poor choices",
   "album": "The FALLING Saga : Act II",
   "albumArt": "https://raw.githubusercontent.com/yonesaku/googledriveextension/refs/heads/main/ACT%202.png",
   "genre": "clinically insane, crazy, mentally instable",
   "year": 2025
 },
 {
   "fileId": "1Gmv4lTHMEQE_9oYryNn8DVEKg5kC1w_l",
   "artist": "Bad decisions .Poor choices",
   "album": "The FALLING Saga : Act II",
   "albumArt": "https://raw.githubusercontent.com/yonesaku/googledriveextension/refs/heads/main/ACT%202.png",
   "genre": "clinically insane, crazy, mentally instable",
   "year": 2025
 },
 {
   "fileId": "1xh4mc62gC9rcUIvRkvVYqlKyPAMFGLNV",
   "artist": "Bad decisions .Poor choices",
   "album": "The FALLING Saga : Act II",
   "albumArt": "https://raw.githubusercontent.com/yonesaku/googledriveextension/refs/heads/main/ACT%202.png",
   "genre": "clinically insane, crazy, mentally instable",
   "year": 2025
 },
 {
   "fileId": "1Lo6lYgnE0phyMOntYmt0iqW31ohwFMgv",
   "artist": "Bad decisions .Poor choices",
   "album": "The FALLING Saga : Act II",
   "albumArt": "https://raw.githubusercontent.com/yonesaku/googledriveextension/refs/heads/main/ACT%202.png",
   "genre": "clinically insane, crazy, mentally instable",
   "year": 2025
 },
 {
   "fileId": "1YftoZc9pmg8qO3I5zjsRV8aNw-Od2cMR",
   "artist": "Bad decisions .Poor choices",
   "album": "The FALLING Saga : Act II",
   "albumArt": "https://raw.githubusercontent.com/yonesaku/googledriveextension/refs/heads/main/ACT%202.png",
   "genre": "clinically insane, crazy, mentally instable",
   "year": 2025
 },
 {
   "fileId": "1Up3w5PJS9nfMczJZ48GJLe2JX2vSP8S5",
   "artist": "Bad decisions .Poor choices",
   "album": "The FALLING Saga : Act II",
   "albumArt": "https://raw.githubusercontent.com/yonesaku/googledriveextension/refs/heads/main/ACT%202.png",
   "genre": "clinically insane, crazy, mentally instable",
   "year": 2025
 },
 {
   "fileId": "1k04RMEjtG0MSDIEQFX5mQlQ3AQ2eb7aC",
   "artist": "Bad decisions .Poor choices",
   "album": "The FALLING Saga : Act II",
   "albumArt": "https://raw.githubusercontent.com/yonesaku/googledriveextension/refs/heads/main/ACT%202.png",
   "genre": "clinically insane, crazy, mentally instable",
   "year": 2025
 },
 {
   "fileId": "12ETxXVa83kcpSQQ9d6a1_0YYgKBfBJ7I",
   "artist": "Bad decisions .Poor choices",
   "album": "The FALLING Saga : Act II",
   "albumArt": "https://raw.githubusercontent.com/yonesaku/googledriveextension/refs/heads/main/ACT%202.png",
   "genre": "clinically insane, crazy, mentally instable",
   "year": 2025
 },
 {
   "fileId": "1VrMSSwnDJQ4Abuctp89DSKlPOpiH2_td",
   "artist": "Bad decisions .Poor choices",
   "album": "The FALLING Saga : Act II",
   "albumArt": "https://raw.githubusercontent.com/yonesaku/googledriveextension/refs/heads/main/ACT%202.png",
   "genre": "clinically insane, crazy, mentally instable",
   "year": 2025
 },
 {
   "fileId": "15wHJlDS0yVfXYDsGKJfCO5nkBf0ZJheW",
   "artist": "Bad decisions .Poor choices",
   "album": "The FALLING Saga : Act II",
   "albumArt": "https://raw.githubusercontent.com/yonesaku/googledriveextension/refs/heads/main/ACT%202.png",
   "genre": "clinically insane, crazy, mentally instable",
   "year": 2025
 },
 {
   "fileId": "1X_D7jChN28FMgc39nqEp1nQr3umXW25E",
   "artist": "Bad decisions .Poor choices",
   "album": "The FALLING Saga : Act II",
   "albumArt": "https://raw.githubusercontent.com/yonesaku/googledriveextension/refs/heads/main/ACT%202.png",
   "genre": "clinically insane, crazy, mentally instable",
   "year": 2025
 },
 {
   "fileId": "1Qa97mh3220VYaTw2rLSzi1AVVgJArgVL",
   "artist": "Bad decisions .Poor choices",
   "album": "The FALLING Saga : Act II",
   "albumArt": "https://raw.githubusercontent.com/yonesaku/googledriveextension/refs/heads/main/ACT%202.png",
   "genre": "clinically insane, crazy, mentally instable",
   "year": 2025
 },
 {
   "fileId": "1FiRn8cJ7Kk2jPAMm16mTB2jF3R9bnaWw",
   "artist": "Bad decisions .Poor choices",
   "album": "The FALLING Saga : Act II",
   "albumArt": "https://raw.githubusercontent.com/yonesaku/googledriveextension/refs/heads/main/ACT%202.png",
   "genre": "clinically insane, crazy, mentally instable",
   "year": 2025
 },
 {
   "fileId": "1mhSAo4ICohMHirxeklB0T6x-saXnfvhJ",
   "artist": "Bad decisions .Poor choices",
   "album": "The FALLING Saga : Act II",
   "albumArt": "https://raw.githubusercontent.com/yonesaku/googledriveextension/refs/heads/main/ACT%202.png",
   "genre": "clinically insane, crazy, mentally instable",
   "year": 2025
 },
 {
   "fileId": "10IPsmpHsaW3eTlmPwIS0fUXV5WicuM1M",
   "artist": "Poor choices . Bad decisions",
   "album": "The FALLING Saga : Act IV",
   "albumArt": "https://raw.githubusercontent.com/yonesaku/googledriveextension/refs/heads/main/ACT%204.png",
   "genre": "clinically insane, crazy, mentally instable",
   "year": 2025
 },
 {
   "fileId": "1DFmqiiV6zV9UgqmaTa6CEiGkBY6SpIVY",
   "artist": "Poor choices . Bad decisions",
   "album": "The FALLING Saga : Act IV",
   "albumArt": "https://raw.githubusercontent.com/yonesaku/googledriveextension/refs/heads/main/ACT%204.png",
   "genre": "clinically insane, crazy, mentally instable",
   "year": 2025
 },
 {
   "fileId": "1qomvCuVQ-qiiU0M1k2BWCRPoGdl_yfME",
   "artist": "Poor choices . Bad decisions",
   "album": "The FALLING Saga : Act IV",
   "albumArt": "https://raw.githubusercontent.com/yonesaku/googledriveextension/refs/heads/main/ACT%204.png",
   "genre": "clinically insane, crazy, mentally instable",
   "year": 2025
 },
 {
   "fileId": "1k1THKtD-TkJTJ9vFUkI8bL8ybSr-_xYe",
   "artist": "Poor choices . Bad decisions",
   "album": "The FALLING Saga : Act IV",
   "albumArt": "https://raw.githubusercontent.com/yonesaku/googledriveextension/refs/heads/main/ACT%204.png",
   "genre": "clinically insane, crazy, mentally instable",
   "year": 2025
 },
 {
   "fileId": "10jonC5q8pHQZwzlTZUGdafXq7aFmjPgh",
   "artist": "Poor choices . Bad decisions",
   "album": "The FALLING Saga : Act IV",
   "albumArt": "https://raw.githubusercontent.com/yonesaku/googledriveextension/refs/heads/main/ACT%204.png",
   "genre": "clinically insane, crazy, mentally instable",
   "year": 2025
 },
 {
   "fileId": "1Tfte89HmElod6HMiDNwJtJGXCOeQFKPV",
   "artist": "Poor choices . Bad decisions",
   "album": "The FALLING Saga : Act IV",
   "albumArt": "https://raw.githubusercontent.com/yonesaku/googledriveextension/refs/heads/main/ACT%204.png",
   "genre": "clinically insane, crazy, mentally instable",
   "year": 2025
 },
 {
   "fileId": "1Gt2I2mtmk5_Gl4vKA49eaPh6_yaemiKL",
   "artist": "Poor choices . Bad decisions",
   "album": "The FALLING Saga : Act IV",
   "albumArt": "https://raw.githubusercontent.com/yonesaku/googledriveextension/refs/heads/main/ACT%204.png",
   "genre": "clinically insane, crazy, mentally instable",
   "year": 2025
 },
 {
   "fileId": "1Ocxh7-OiXmJtFADpdC1XCioNbw-R6Pb-",
   "artist": "Poor choices . Bad decisions",
   "album": "The FALLING Saga : Act IV",
   "albumArt": "https://raw.githubusercontent.com/yonesaku/googledriveextension/refs/heads/main/ACT%204.png",
   "genre": "clinically insane, crazy, mentally instable",
   "year": 2025
 },
 {
   "fileId": "10N9biQE_rTqLgjj4GaEg4tRB3KlMQEt2",
   "artist": "Poor choices . Bad decisions",
   "album": "The FALLING Saga : Act IV",
   "albumArt": "https://raw.githubusercontent.com/yonesaku/googledriveextension/refs/heads/main/ACT%204.png",
   "genre": "clinically insane, crazy, mentally instable",
   "year": 2025
 },
 {
   "fileId": "1Qx3PSOnImjGtsK2l5uQ1LeUc12UtPkOs",
   "artist": "Poor choices . Bad decisions",
   "album": "The FALLING Saga : Act IV",
   "albumArt": "https://raw.githubusercontent.com/yonesaku/googledriveextension/refs/heads/main/ACT%204.png",
   "genre": "clinically insane, crazy, mentally instable",
   "year": 2025
 },
 {
   "fileId": "1ePm99A3xx70NyT8bmoDrk-HZ8p9n-iWQ",
   "artist": "Poor choices . Bad decisions",
   "album": "The FALLING Saga : Act IV",
   "albumArt": "https://raw.githubusercontent.com/yonesaku/googledriveextension/refs/heads/main/ACT%204.png",
   "genre": "clinically insane, crazy, mentally instable",
   "year": 2025
 },
 {
   "fileId": "153emFeY3HwgKE318wQewnZSJ0rSuhvlC",
   "artist": "Poor choices . Bad decisions",
   "album": "The FALLING Saga : Act IV",
   "albumArt": "https://raw.githubusercontent.com/yonesaku/googledriveextension/refs/heads/main/ACT%204.png",
   "genre": "clinically insane, crazy, mentally instable",
   "year": 2025
 },
 {
   "fileId": "1RlVbjZh59eWmGzo2e9LAMcOBiah1lHvw",
   "artist": "Poor choices . Bad decisions",
   "album": "The FALLING Saga : Act IV",
   "albumArt": "https://raw.githubusercontent.com/yonesaku/googledriveextension/refs/heads/main/ACT%204.png",
   "genre": "clinically insane, crazy, mentally instable",
   "year": 2025
 },
 {
   "fileId": "1uLtvLX77PjKhrhXkkhyWpkWk3gianexQ",
   "artist": "Poor choices . Bad decisions",
   "album": "The FALLING Saga : Act IV",
   "albumArt": "https://raw.githubusercontent.com/yonesaku/googledriveextension/refs/heads/main/ACT%204.png",
   "genre": "clinically insane, crazy, mentally instable",
   "year": 2025
 },
 {
   "fileId": "1RJC15eP-3-UEe-lZDt944EbXJgE0x65k",
   "artist": "Poor choices . Bad decisions",
   "album": "The FALLING Saga : Act IV",
   "albumArt": "https://raw.githubusercontent.com/yonesaku/googledriveextension/refs/heads/main/ACT%204.png",
   "genre": "clinically insane, crazy, mentally instable",
   "year": 2025
 },
 {
   "fileId": "1b_OA-RIBaceTryWOwhA06uHM0swCZBdF",
   "artist": "Poor choices . Bad decisions",
   "album": "The FALLING Saga : Act IV",
   "albumArt": "https://raw.githubusercontent.com/yonesaku/googledriveextension/refs/heads/main/ACT%204.png",
   "genre": "clinically insane, crazy, mentally instable",
   "year": 2025
 },
 {
   "fileId": "1QxrR4Pw9Ncehf7F9WXm3BTlwTM2B0G68",
   "artist": "Poor choices . Bad decisions",
   "album": "The FALLING Saga : Act IV",
   "albumArt": "https://raw.githubusercontent.com/yonesaku/googledriveextension/refs/heads/main/ACT%204.png",
   "genre": "clinically insane, crazy, mentally instable",
   "year": 2025
 },
 {
   "fileId": "1aOE74rfbI_w_zntP0kTf3gNCBCsREef7",
   "artist": "Poor choices . Bad decisions",
   "album": "The FALLING Saga : Act IV",
   "albumArt": "https://raw.githubusercontent.com/yonesaku/googledriveextension/refs/heads/main/ACT%204.png",
   "genre": "clinically insane, crazy, mentally instable",
   "year": 2025
 },
 {
   "fileId": "1iXHQmbqk-0kWmWPnE3Z_n_JJvcxdDXWq",
   "artist": "Poor choices . Bad decisions",
   "album": "The FALLING Saga : Act IV",
   "albumArt": "https://raw.githubusercontent.com/yonesaku/googledriveextension/refs/heads/main/ACT%204.png",
   "genre": "clinically insane, crazy, mentally instable",
   "year": 2025
 },
 {
   "fileId": "1TXDACLroYZKSqB55d78upYXe5kTdmGGi",
   "artist": "Poor choices . Bad decisions",
   "album": "The FALLING Saga : Act IV",
   "albumArt": "https://raw.githubusercontent.com/yonesaku/googledriveextension/refs/heads/main/ACT%204.png",
   "genre": "clinically insane, crazy, mentally instable",
   "year": 2025
 },
 {
   "fileId": "1Gaa8F0imI11AzQ_LiQ8JXXSRgP_CwKo3",
   "artist": "Poor choices . Bad decisions",
   "album": "The FALLING Saga : Act IV",
   "albumArt": "https://raw.githubusercontent.com/yonesaku/googledriveextension/refs/heads/main/ACT%204.png",
   "genre": "clinically insane, crazy, mentally instable",
   "year": 2025
 },
 {
   "fileId": "1ygjztBlAHNs3QFAvtiolFwnFJY9wEMPW",
   "artist": "Poor choices . Bad decisions",
   "album": "The FALLING Saga : Act IV",
   "albumArt": "https://raw.githubusercontent.com/yonesaku/googledriveextension/refs/heads/main/ACT%204.png",
   "genre": "clinically insane, crazy, mentally instable",
   "year": 2025
 },
 {
   "fileId": "1ybeQjJZpqDjnADwPeKlU6AuK9-6V9Q4T",
   "artist": "Poor choices . Bad decisions",
   "album": "The FALLING Saga : Act IV",
   "albumArt": "https://raw.githubusercontent.com/yonesaku/googledriveextension/refs/heads/main/ACT%204.png",
   "genre": "clinically insane, crazy, mentally instable",
   "year": 2025
 },
 {
   "fileId": "1vTeivWpYhbKrgjkIwB9Ya-zPbdPDIIDi",
   "artist": "Poor choices . Bad decisions",
   "album": "The FALLING Saga : Act IV",
   "albumArt": "https://raw.githubusercontent.com/yonesaku/googledriveextension/refs/heads/main/ACT%204.png",
   "genre": "clinically insane, crazy, mentally instable",
   "year": 2025
 },
 {
   "fileId": "1mGYCkWL7DRflVBHpzyVshHqg1BhYcA4J",
   "artist": "Poor choices . Bad decisions",
   "album": "The FALLING Saga : Act IV",
   "albumArt": "https://raw.githubusercontent.com/yonesaku/googledriveextension/refs/heads/main/ACT%204.png",
   "genre": "clinically insane, crazy, mentally instable",
   "year": 2025
 },
 {
   "fileId": "14B0S3hOq-R-tl-UpVFWwHezXEf9fBozP",
   "artist": "Poor choices . Bad decisions",
   "album": "The FALLING Saga : Act IV",
   "albumArt": "https://raw.githubusercontent.com/yonesaku/googledriveextension/refs/heads/main/ACT%204.png",
   "genre": "clinically insane, crazy, mentally instable",
   "year": 2025
 },
 {
   "fileId": "1WpRoI0H3v03qHKgjei6x0znzgXkrCLJ1",
   "artist": "Poor choices . Bad decisions",
   "album": "The FALLING Saga : Act IV",
   "albumArt": "https://raw.githubusercontent.com/yonesaku/googledriveextension/refs/heads/main/ACT%204.png",
   "genre": "clinically insane, crazy, mentally instable",
   "year": 2025
 },
 {
   "fileId": "1OIe720iO_HYJjJgVorwLzmdTSjPEBYuK",
   "artist": "Poor choices . Bad decisions",
   "album": "The FALLING Saga : Act IV",
   "albumArt": "https://raw.githubusercontent.com/yonesaku/googledriveextension/refs/heads/main/ACT%204.png",
   "genre": "clinically insane, crazy, mentally instable",
   "year": 2025
 },
 {
   "fileId": "1sQOTvdIa-eM4XzdxnCAReG8sIB2zxuaZ",
   "artist": "Poor choices . Bad decisions",
   "album": "The FALLING Saga : Act IV",
   "albumArt": "https://raw.githubusercontent.com/yonesaku/googledriveextension/refs/heads/main/ACT%204.png",
   "genre": "clinically insane, crazy, mentally instable",
   "year": 2025
 },
 {
   "fileId": "1RX-4HgZriDCk4yIWV5d4WF3f0b01_HNy",
   "artist": "Poor choices . Bad decisions",
   "album": "The FALLING Saga : Act IV",
   "albumArt": "https://raw.githubusercontent.com/yonesaku/googledriveextension/refs/heads/main/ACT%204.png",
   "genre": "clinically insane, crazy, mentally instable",
   "year": 2025
 },
 {
   "fileId": "1BphGA1RmremoKP0CwHeyave-5cUAsmr_",
   "artist": "Poor choices . Bad decisions",
   "album": "The FALLING Saga : Act IV",
   "albumArt": "https://raw.githubusercontent.com/yonesaku/googledriveextension/refs/heads/main/ACT%204.png",
   "genre": "clinically insane, crazy, mentally instable",
   "year": 2025
 },
 {
   "fileId": "180uXqJ3P778SfMoKLYsmDxc1NypAdqFe",
   "artist": "Poor choices . Bad decisions",
   "album": "The FALLING Saga : Act IV",
   "albumArt": "https://raw.githubusercontent.com/yonesaku/googledriveextension/refs/heads/main/ACT%204.png",
   "genre": "clinically insane, crazy, mentally instable",
   "year": 2025
 },
 {
   "fileId": "1-aaNWBsQ82UjkuUW9yjZXI0sAEwodJsa",
   "artist": "Poor choices . Bad decisions",
   "album": "The FALLING Saga : Act IV",
   "albumArt": "https://raw.githubusercontent.com/yonesaku/googledriveextension/refs/heads/main/ACT%204.png",
   "genre": "clinically insane, crazy, mentally instable",
   "year": 2025
 },
 {
   "fileId": "1k0Gnj7SvA0UM6wI7SEaSxiW0wzb1vF4H",
   "artist": "Poor choices . Bad decisions",
   "album": "The FALLING Saga : Act IV",
   "albumArt": "https://raw.githubusercontent.com/yonesaku/googledriveextension/refs/heads/main/ACT%204.png",
   "genre": "clinically insane, crazy, mentally instable",
   "year": 2025
 },
 {
   "fileId": "1RhAcx5UeRfs77WTP0bPvh_7mvq60UVID",
   "artist": "Poor choices . Bad decisions",
   "album": "The FALLING Saga : Act IV",
   "albumArt": "https://raw.githubusercontent.com/yonesaku/googledriveextension/refs/heads/main/ACT%204.png",
   "genre": "clinically insane, crazy, mentally instable",
   "year": 2025
 },
 {
   "fileId": "1HJj-vPR4FxVssRc0OPhFghjZEIDb7m_8",
   "artist": "Poor choices . Bad decisions",
   "album": "The FALLING Saga : Act IV",
   "albumArt": "https://raw.githubusercontent.com/yonesaku/googledriveextension/refs/heads/main/ACT%204.png",
   "genre": "clinically insane, crazy, mentally instable",
   "year": 2025
 },
 {
   "fileId": "15lqm76kpMvE_g6EG-GnrZk7g2AseTJE8",
   "artist": "Poor choices . Bad decisions",
   "album": "The FALLING Saga : Act IV",
   "albumArt": "https://raw.githubusercontent.com/yonesaku/googledriveextension/refs/heads/main/ACT%204.png",
   "genre": "clinically insane, crazy, mentally instable",
   "year": 2025
 },
 {
   "fileId": "1TTNLt3gSUWEgpMdWM0khGKlg7V6sqnHc",
   "artist": "Poor choices . Bad decisions",
   "album": "The FALLING Saga : Act IV",
   "albumArt": "https://raw.githubusercontent.com/yonesaku/googledriveextension/refs/heads/main/ACT%204.png",
   "genre": "clinically insane, crazy, mentally instable",
   "year": 2025
 },
 {
   "fileId": "1M-14ZJINz2THvty77G7KCihzoqaPxjmV",
   "artist": "Poor choices . Bad decisions",
   "album": "The FALLING Saga : Act IV",
   "albumArt": "https://raw.githubusercontent.com/yonesaku/googledriveextension/refs/heads/main/ACT%204.png",
   "genre": "clinically insane, crazy, mentally instable",
   "year": 2025
 },
 {
   "fileId": "1xWpnbfduFeDbS-MgfZVx3RFZZox9Abvw",
   "artist": "Poor choices . Bad decisions",
   "album": "The FALLING Saga : Act IV",
   "albumArt": "https://raw.githubusercontent.com/yonesaku/googledriveextension/refs/heads/main/ACT%204.png",
   "genre": "clinically insane, crazy, mentally instable",
   "year": 2025
 },
 {
   "fileId": "143841ghFjDeRuXLKzTT4Hgq-2uo1sZcI",
   "artist": "Poor choices . Bad decisions",
   "album": "The FALLING Saga : Act IV",
   "albumArt": "https://raw.githubusercontent.com/yonesaku/googledriveextension/refs/heads/main/ACT%204.png",
   "genre": "clinically insane, crazy, mentally instable",
   "year": 2025
 },
 {
   "fileId": "190sZSooZKiaJLKFgqkgX17tKNyEEjxA0",
   "artist": "Poor choices . Bad decisions",
   "album": "The FALLING Saga : Act IV",
   "albumArt": "https://raw.githubusercontent.com/yonesaku/googledriveextension/refs/heads/main/ACT%204.png",
   "genre": "clinically insane, crazy, mentally instable",
   "year": 2025
 },
 {
   "fileId": "18B5xUzA7uz3Q40BCcpm1IXeBJO9neiLV",
   "artist": "Poor choices . Bad decisions",
   "album": "The FALLING Saga : Act IV",
   "albumArt": "https://raw.githubusercontent.com/yonesaku/googledriveextension/refs/heads/main/ACT%204.png",
   "genre": "clinically insane, crazy, mentally instable",
   "year": 2025
 },
 {
   "fileId": "1EVUU-uIS7Ts6PnvqayUe4CitBjWeIaEK",
   "artist": "Poor choices . Bad decisions",
   "album": "The FALLING Saga : Act IV",
   "albumArt": "https://raw.githubusercontent.com/yonesaku/googledriveextension/refs/heads/main/ACT%204.png",
   "genre": "clinically insane, crazy, mentally instable",
   "year": 2025
 },
 {
   "fileId": "1qErMNlU1mpta9vDXv6sqK9F_jfGAXk09",
   "artist": "Poor choices . Bad decisions",
   "album": "The FALLING Saga : Act IV",
   "albumArt": "https://raw.githubusercontent.com/yonesaku/googledriveextension/refs/heads/main/ACT%204.png",
   "genre": "clinically insane, crazy, mentally instable",
   "year": 2025
 },
 {
   "fileId": "1LTBnV1DAJVnhn_cdZJh5rAz86FpOIREq",
   "artist": "Poor choices . Bad decisions",
   "album": "The FALLING Saga : Act IV",
   "albumArt": "https://raw.githubusercontent.com/yonesaku/googledriveextension/refs/heads/main/ACT%204.png",
   "genre": "clinically insane, crazy, mentally instable",
   "year": 2025
 },
 {
   "fileId": "17592nKZGBgiH_Y4VPbnMZjc0SEDD0c7F",
   "artist": "Poor choices . Bad decisions",
   "album": "The FALLING Saga : Act IV",
   "albumArt": "https://raw.githubusercontent.com/yonesaku/googledriveextension/refs/heads/main/ACT%204.png",
   "genre": "clinically insane, crazy, mentally instable",
   "year": 2025
 },
 {
   "fileId": "11jxjvQemNm6R7PuPhUssNB3n8WO9S4bE",
   "artist": "Poor choices . Bad decisions",
   "album": "The FALLING Saga : Act IV",
   "albumArt": "https://raw.githubusercontent.com/yonesaku/googledriveextension/refs/heads/main/ACT%204.png",
   "genre": "clinically insane, crazy, mentally instable",
   "year": 2025
 }
]
   }